storex-0.0a0.dist-info/METADATA
storex-0.0a0.dist-info/WHEEL
storex/__init__.py
storex/proto.py
storex-0.0a0.dist-info/RECORD
