Metadata-Version: 2.1
Name: storex
Version: 0.0a0
Summary: Default template for PDM package
Author-Email: Arwichok <arwichok@gmail.com>
License: MIT
Requires-Python: >=3.8
